facer/__init__.py
facer_model-1.0.8.dist-info/licenses/LICENCE.txt
facer_model-1.0.8.dist-info/METADATA
facer_model-1.0.8.dist-info/WHEEL
facer_model-1.0.8.dist-info/top_level.txt
facer_model-1.0.8.dist-info/RECORD
