Metadata-Version: 2.4
Name: facer-model
Version: 1.0.8
Summary: The Birkeland current model presented by Coxon et al. (2016), based on Milan (2013).
Author-email: John C Coxon <work@johncoxon.co.uk>, Stephen E Milan <steve.milan@leicester.ac.uk>
Maintainer-email: John C Coxon <work@johncoxon.co.uk>, Matthew J Townson <matthew.townson@northumbria.ac.uk>
License-Expression: AGPL-3.0-or-later
Project-URL: doi, https://doi.org/10.5281/zenodo.15731338
Project-URL: repository, https://github.com/johncoxon/facer-model
Keywords: Birkeland currents,field-aligned currents,magnetic reconnection
Classifier: Development Status :: 4 - Beta
Classifier: Intended Audience :: Science/Research
Classifier: Natural Language :: English
Classifier: Programming Language :: Python :: 3
Classifier: Topic :: Scientific/Engineering :: Physics
Requires-Python: >=3.9
License-File: LICENCE.txt
Requires-Dist: matplotlib
Requires-Dist: numpy
Requires-Dist: pandas
Dynamic: license-file
